[
    {
        "energy": 8,
        "nameid": "ACID",
        "buffChance": 0,
        "buffSelf": false,
        "buffEffect": "",
        "name": "Acid",
        "type": "poison",
        "damage": 6,
        "turns": 2
    },
    {
        "energy": 45,
        "nameid": "ACID_SPRAY",
        "buffChance": "1",
        "buffSelf": false,
        "buffEffect": " -2 DEF",
        "name": "Acid Spray",
        "type": "poison",
        "damage": 20,
        "turns": 0
    },
    {
        "energy": 55,
        "nameid": "ACROBATICS",
        "buffChance": 0,
        "buffSelf": false,
        "buffEffect": "",
        "name": "Acrobatics",
        "type": "flying",
        "damage": 110,
        "turns": 0
    },
    {
        "energy": 6,
        "nameid": "AEGISLASH_CHARGE_AIR_SLASH",
        "buffChance": 0,
        "buffSelf": false,
        "buffEffect": "",
        "name": "Air Slash",
        "type": "flying",
        "damage": 0,
        "turns": 3
    },
    {
        "energy": 6,
        "nameid": "AEGISLASH_CHARGE_PSYCHO_CUT",
        "buffChance": 0,
        "buffSelf": false,
        "buffEffect": "",
        "name": "Psycho Cut",
        "type": "psychic",
        "damage": 0,
        "turns": 2
    },
    {
        "energy": 45,
        "nameid": "AERIAL_ACE",
        "buffChance": 0,
        "buffSelf": false,
        "buffEffect": "",
        "name": "Aerial Ace",
        "type": "flying",
        "damage": 60,
        "turns": 0
    },
    {
        "energy": 75,
        "nameid": "AEROBLAST",
        "buffChance": ".125",
        "buffSelf": true,
        "buffEffect": "+2 ATK",
        "name": "Aeroblast",
        "type": "flying",
        "damage": 170,
        "turns": 0
    },
    {
        "energy": 35,
        "nameid": "AIR_CUTTER",
        "buffChance": ".3",
        "buffSelf": true,
        "buffEffect": "+1 ATK",
        "name": "Air Cutter",
        "type": "flying",
        "damage": 45,
        "turns": 0
    },
    {
        "energy": 9,
        "nameid": "AIR_SLASH",
        "buffChance": 0,
        "buffSelf": false,
        "buffEffect": "",
        "name": "Air Slash",
        "type": "flying",
        "damage": 9,
        "turns": 3
    },
    {
        "energy": 45,
        "nameid": "ANCIENT_POWER",
        "buffChance": ".1",
        "buffSelf": true,
        "buffEffect": "+1 ATK +1 DEF",
        "name": "Ancient Power",
        "type": "rock",
        "damage": 60,
        "turns": 0
    },
    {
        "energy": 40,
        "nameid": "AQUA_JET",
        "buffChance": 0,
        "buffSelf": false,
        "buffEffect": "",
        "name": "Aqua Jet",
        "type": "water",
        "damage": 70,
        "turns": 0
    },
    {
        "energy": 40,
        "nameid": "AQUA_STEP",
        "buffChance": "1",
        "buffSelf": true,
        "buffEffect": "+1 ATK",
        "name": "Aqua Step",
        "type": "water",
        "damage": 55,
        "turns": 0
    },
    {
        "energy": 35,
        "nameid": "AQUA_TAIL",
        "buffChance": 0,
        "buffSelf": false,
        "buffEffect": "",
        "name": "Aqua Tail",
        "type": "water",
        "damage": 55,
        "turns": 0
    },
    {
        "energy": 10,
        "nameid": "ASTONISH",
        "buffChance": 0,
        "buffSelf": false,
        "buffEffect": "",
        "name": "Astonish",
        "type": "ghost",
        "damage": 12,
        "turns": 3
    },
    {
        "energy": 40,
        "nameid": "AURA_SPHERE",
        "buffChance": 0,
        "buffSelf": false,
        "buffEffect": "",
        "name": "Aura Sphere",
        "type": "fighting",
        "damage": 80,
        "turns": 0
    },
    {
        "energy": 45,
        "nameid": "AURA_WHEEL_DARK",
        "buffChance": "1",
        "buffSelf": true,
        "buffEffect": "+1 ATK",
        "name": "Aura Wheel",
        "type": "dark",
        "damage": 100,
        "turns": 0
    },
    {
        "energy": 45,
        "nameid": "AURA_WHEEL_ELECTRIC",
        "buffChance": "1",
        "buffSelf": true,
        "buffEffect": "+1 ATK",
        "name": "Aura Wheel",
        "type": "electric",
        "damage": 100,
        "turns": 0
    },
    {
        "energy": 60,
        "nameid": "AURORA_BEAM",
        "buffChance": 0,
        "buffSelf": false,
        "buffEffect": "",
        "name": "Aurora Beam",
        "type": "ice",
        "damage": 80,
        "turns": 0
    },
    {
        "energy": 45,
        "nameid": "AVALANCHE",
        "buffChance": 0,
        "buffSelf": false,
        "buffEffect": "",
        "name": "Avalanche",
        "type": "ice",
        "damage": 90,
        "turns": 0
    },
    {
        "energy": 55,
        "nameid": "BEAK_BLAST",
        "buffChance": "1",
        "buffSelf": false,
        "buffEffect": "-1 ATK",
        "name": "Beak Blast",
        "type": "flying",
        "damage": 110,
        "turns": 0
    },
    {
        "energy": 45,
        "nameid": "BEHEMOTH_BASH",
        "buffChance": 0,
        "buffSelf": false,
        "buffEffect": "",
        "name": "Behemoth Bash",
        "type": "steel",
        "damage": 80,
        "turns": 0
    },
    {
        "energy": 55,
        "nameid": "BEHEMOTH_BLADE",
        "buffChance": 0,
        "buffSelf": false,
        "buffEffect": "",
        "name": "Behemoth Blade",
        "type": "steel",
        "damage": 100,
        "turns": 0
    },
    {
        "energy": 2,
        "nameid": "BITE",
        "buffChance": 0,
        "buffSelf": false,
        "buffEffect": "",
        "name": "Bite",
        "type": "dark",
        "damage": 4,
        "turns": 1
    },
    {
        "energy": 50,
        "nameid": "BLAST_BURN",
        "buffChance": 0,
        "buffSelf": false,
        "buffEffect": "",
        "name": "Blast Burn",
        "type": "fire",
        "damage": 110,
        "turns": 0
    },
    {
        "energy": 40,
        "nameid": "BLAZE_KICK",
        "buffChance": 0,
        "buffSelf": false,
        "buffEffect": "",
        "name": "Blaze Kick",
        "type": "fire",
        "damage": 60,
        "turns": 0
    },
    {
        "energy": 45,
        "nameid": "BLEAKWIND_STORM",
        "buffChance": "1",
        "buffSelf": false,
        "buffEffect": "-1 ATK",
        "name": "Bleakwind Storm",
        "type": "flying",
        "damage": 60,
        "turns": 0
    },
    {
        "energy": 75,
        "nameid": "BLIZZARD",
        "buffChance": 0,
        "buffSelf": false,
        "buffEffect": "",
        "name": "Blizzard",
        "type": "ice",
        "damage": 140,
        "turns": 0
    },
    {
        "energy": 35,
        "nameid": "BODY_SLAM",
        "buffChance": 0,
        "buffSelf": false,
        "buffEffect": "",
        "name": "Body Slam",
        "type": "normal",
        "damage": 55,
        "turns": 0
    },
    {
        "energy": 35,
        "nameid": "BONE_CLUB",
        "buffChance": 0,
        "buffSelf": false,
        "buffEffect": "",
        "name": "Bone Club",
        "type": "ground",
        "damage": 55,
        "turns": 0
    },
    {
        "energy": 70,
        "nameid": "BOOMBURST",
        "buffChance": 0,
        "buffSelf": false,
        "buffEffect": "",
        "name": "Boomburst",
        "type": "normal",
        "damage": 150,
        "turns": 0
    },
    {
        "energy": 55,
        "nameid": "BRAVE_BIRD",
        "buffChance": "1",
        "buffSelf": true,
        "buffEffect": " -3 DEF",
        "name": "Brave Bird",
        "type": "flying",
        "damage": 130,
        "turns": 0
    },
    {
        "energy": 50,
        "nameid": "BREAKING_SWIPE",
        "buffChance": "1",
        "buffSelf": false,
        "buffEffect": "-1 ATK",
        "name": "Breaking Swipe",
        "type": "dragon",
        "damage": 50,
        "turns": 0
    },
    {
        "energy": 40,
        "nameid": "BRICK_BREAK",
        "buffChance": "1",
        "buffSelf": false,
        "buffEffect": " -1 DEF",
        "name": "Brick Break",
        "type": "fighting",
        "damage": 50,
        "turns": 0
    },
    {
        "energy": 50,
        "nameid": "BRINE",
        "buffChance": 0,
        "buffSelf": false,
        "buffEffect": "",
        "name": "Brine",
        "type": "water",
        "damage": 60,
        "turns": 0
    },
    {
        "energy": 35,
        "nameid": "BRUTAL_SWING",
        "buffChance": 0,
        "buffSelf": false,
        "buffEffect": "",
        "name": "Brutal Swing",
        "type": "dark",
        "damage": 55,
        "turns": 0
    },
    {
        "energy": 11,
        "nameid": "BUBBLE",
        "buffChance": 0,
        "buffSelf": false,
        "buffEffect": "",
        "name": "Bubble",
        "type": "water",
        "damage": 8,
        "turns": 3
    },
    {
        "energy": 40,
        "nameid": "BUBBLE_BEAM",
        "buffChance": "1",
        "buffSelf": false,
        "buffEffect": "-1 ATK",
        "name": "Bubble Beam",
        "type": "water",
        "damage": 25,
        "turns": 0
    },
    {
        "energy": 3,
        "nameid": "BUG_BITE",
        "buffChance": 0,
        "buffSelf": false,
        "buffEffect": "",
        "name": "Bug Bite",
        "type": "bug",
        "damage": 4,
        "turns": 1
    },
    {
        "energy": 60,
        "nameid": "BUG_BUZZ",
        "buffChance": ".3",
        "buffSelf": false,
        "buffEffect": " -1 DEF",
        "name": "Bug Buzz",
        "type": "bug",
        "damage": 100,
        "turns": 0
    },
    {
        "energy": 45,
        "nameid": "BULLDOZE",
        "buffChance": ".5",
        "buffSelf": false,
        "buffEffect": " -1 DEF",
        "name": "Bulldoze",
        "type": "ground",
        "damage": 45,
        "turns": 0
    },
    {
        "energy": 7,
        "nameid": "BULLET_PUNCH",
        "buffChance": 0,
        "buffSelf": false,
        "buffEffect": "",
        "name": "Bullet Punch",
        "type": "steel",
        "damage": 8,
        "turns": 2
    },
    {
        "energy": 13,
        "nameid": "BULLET_SEED",
        "buffChance": 0,
        "buffSelf": false,
        "buffEffect": "",
        "name": "Bullet Seed",
        "type": "grass",
        "damage": 5,
        "turns": 3
    },
    {
        "energy": 11,
        "nameid": "CHARGE_BEAM",
        "buffChance": 0,
        "buffSelf": false,
        "buffEffect": "",
        "name": "Charge Beam",
        "type": "electric",
        "damage": 5,
        "turns": 3
    },
    {
        "energy": 8,
        "nameid": "CHARM",
        "buffChance": 0,
        "buffSelf": false,
        "buffEffect": "",
        "name": "Charm",
        "type": "fairy",
        "damage": 13,
        "turns": 3
    },
    {
        "energy": 45,
        "nameid": "CHILLING_WATER",
        "buffChance": "1",
        "buffSelf": false,
        "buffEffect": "-1 ATK",
        "name": "Chilling Water",
        "type": "water",
        "damage": 60,
        "turns": 0
    },
    {
        "energy": 45,
        "nameid": "CLANGING_SCALES",
        "buffChance": "1",
        "buffSelf": true,
        "buffEffect": " -1 DEF",
        "name": "Clanging Scales",
        "type": "dragon",
        "damage": 120,
        "turns": 0
    },
    {
        "energy": 45,
        "nameid": "CLOSE_COMBAT",
        "buffChance": "1",
        "buffSelf": true,
        "buffEffect": " -2 DEF",
        "name": "Close Combat",
        "type": "fighting",
        "damage": 100,
        "turns": 0
    },
    {
        "energy": 14,
        "nameid": "CONFUSION",
        "buffChance": 0,
        "buffSelf": false,
        "buffEffect": "",
        "name": "Confusion",
        "type": "psychic",
        "damage": 16,
        "turns": 4
    },
    {
        "energy": 6,
        "nameid": "COUNTER",
        "buffChance": 0,
        "buffSelf": false,
        "buffEffect": "",
        "name": "Counter",
        "type": "fighting",
        "damage": 8,
        "turns": 2
    },
    {
        "energy": 50,
        "nameid": "CRABHAMMER",
        "buffChance": ".125",
        "buffSelf": true,
        "buffEffect": "+2 ATK",
        "name": "Crabhammer",
        "type": "water",
        "damage": 85,
        "turns": 0
    },
    {
        "energy": 35,
        "nameid": "CROSS_CHOP",
        "buffChance": 0,
        "buffSelf": false,
        "buffEffect": "",
        "name": "Cross Chop",
        "type": "fighting",
        "damage": 55,
        "turns": 0
    },
    {
        "energy": 35,
        "nameid": "CROSS_POISON",
        "buffChance": ".125",
        "buffSelf": true,
        "buffEffect": "+2 ATK",
        "name": "Cross Poison",
        "type": "poison",
        "damage": 50,
        "turns": 0
    },
    {
        "energy": 45,
        "nameid": "CRUNCH",
        "buffChance": "0.2",
        "buffSelf": false,
        "buffEffect": " -1 DEF",
        "name": "Crunch",
        "type": "dark",
        "damage": 70,
        "turns": 0
    },
    {
        "energy": 50,
        "nameid": "CRUSH_GRIP",
        "buffChance": 0,
        "buffSelf": false,
        "buffEffect": "",
        "name": "Crush Grip",
        "type": "normal",
        "damage": 110,
        "turns": 0
    },
    {
        "energy": 2,
        "nameid": "CUT",
        "buffChance": 0,
        "buffSelf": false,
        "buffEffect": "",
        "name": "Cut",
        "type": "normal",
        "damage": 3,
        "turns": 1
    },
    {
        "energy": 60,
        "nameid": "DARKEST_LARIAT",
        "buffChance": 0,
        "buffSelf": false,
        "buffEffect": "",
        "name": "Darkest Lariat",
        "type": "dark",
        "damage": 120,
        "turns": 0
    },
    {
        "energy": 50,
        "nameid": "DARK_PULSE",
        "buffChance": 0,
        "buffSelf": false,
        "buffEffect": "",
        "name": "Dark Pulse",
        "type": "dark",
        "damage": 80,
        "turns": 0
    },
    {
        "energy": 55,
        "nameid": "DAZZLING_GLEAM",
        "buffChance": 0,
        "buffSelf": false,
        "buffEffect": "",
        "name": "Dazzling Gleam",
        "type": "fairy",
        "damage": 90,
        "turns": 0
    },
    {
        "energy": 50,
        "nameid": "DIG",
        "buffChance": 0,
        "buffSelf": false,
        "buffEffect": "",
        "name": "Dig",
        "type": "ground",
        "damage": 70,
        "turns": 0
    },
    {
        "energy": 45,
        "nameid": "DISARMING_VOICE",
        "buffChance": 0,
        "buffSelf": false,
        "buffEffect": "",
        "name": "Disarming Voice",
        "type": "fairy",
        "damage": 70,
        "turns": 0
    },
    {
        "energy": 40,
        "nameid": "DISCHARGE",
        "buffChance": 0,
        "buffSelf": false,
        "buffEffect": "",
        "name": "Discharge",
        "type": "electric",
        "damage": 55,
        "turns": 0
    },
    {
        "energy": 40,
        "nameid": "DOOM_DESIRE",
        "buffChance": 0,
        "buffSelf": false,
        "buffEffect": "",
        "name": "Doom Desire",
        "type": "steel",
        "damage": 80,
        "turns": 0
    },
    {
        "energy": 35,
        "nameid": "DOUBLE_IRON_BASH",
        "buffChance": 0,
        "buffSelf": false,
        "buffEffect": "",
        "name": "Double Iron Bash",
        "type": "steel",
        "damage": 55,
        "turns": 0
    },
    {
        "energy": 12,
        "nameid": "DOUBLE_KICK",
        "buffChance": 0,
        "buffSelf": false,
        "buffEffect": "",
        "name": "Double Kick",
        "type": "fighting",
        "damage": 8,
        "turns": 3
    },
    {
        "energy": 65,
        "nameid": "DRACO_METEOR",
        "buffChance": "1",
        "buffSelf": true,
        "buffEffect": "-2 ATK",
        "name": "Draco Meteor",
        "type": "dragon",
        "damage": 150,
        "turns": 0
    },
    {
        "energy": 70,
        "nameid": "DRAGON_ASCENT",
        "buffChance": "1",
        "buffSelf": true,
        "buffEffect": " -1 DEF",
        "name": "Dragon Ascent",
        "type": "flying",
        "damage": 150,
        "turns": 0
    },
    {
        "energy": 4,
        "nameid": "DRAGON_BREATH",
        "buffChance": 0,
        "buffSelf": false,
        "buffEffect": "",
        "name": "Dragon Breath",
        "type": "dragon",
        "damage": 3,
        "turns": 1
    },
    {
        "energy": 50,
        "nameid": "DRAGON_CLAW",
        "buffChance": 0,
        "buffSelf": false,
        "buffEffect": "",
        "name": "Dragon Claw",
        "type": "dragon",
        "damage": 80,
        "turns": 0
    },
    {
        "energy": 45,
        "nameid": "DRAGON_ENERGY",
        "buffChance": 0,
        "buffSelf": false,
        "buffEffect": "",
        "name": "Dragon Energy",
        "type": "dragon",
        "damage": 90,
        "turns": 0
    },
    {
        "energy": 55,
        "nameid": "DRAGON_PULSE",
        "buffChance": 0,
        "buffSelf": false,
        "buffEffect": "",
        "name": "Dragon Pulse",
        "type": "dragon",
        "damage": 90,
        "turns": 0
    },
    {
        "energy": 12,
        "nameid": "DRAGON_TAIL",
        "buffChance": 0,
        "buffSelf": false,
        "buffEffect": "",
        "name": "Dragon Tail",
        "type": "dragon",
        "damage": 9,
        "turns": 3
    },
    {
        "energy": 55,
        "nameid": "DRAINING_KISS",
        "buffChance": 0,
        "buffSelf": false,
        "buffEffect": "",
        "name": "Draining Kiss",
        "type": "fairy",
        "damage": 60,
        "turns": 0
    },
    {
        "energy": 40,
        "nameid": "DRAIN_PUNCH",
        "buffChance": "1",
        "buffSelf": true,
        "buffEffect": " +1 DEF",
        "name": "Drain Punch",
        "type": "fighting",
        "damage": 20,
        "turns": 0
    },
    {
        "energy": 40,
        "nameid": "DRILL_PECK",
        "buffChance": 0,
        "buffSelf": false,
        "buffEffect": "",
        "name": "Drill Peck",
        "type": "flying",
        "damage": 70,
        "turns": 0
    },
    {
        "energy": 45,
        "nameid": "DRILL_RUN",
        "buffChance": 0,
        "buffSelf": false,
        "buffEffect": "",
        "name": "Drill Run",
        "type": "ground",
        "damage": 80,
        "turns": 0
    },
    {
        "energy": 35,
        "nameid": "DRUM_BEATING",
        "buffChance": "1",
        "buffSelf": false,
        "buffEffect": "-1 ATK",
        "name": "Drum Beating",
        "type": "grass",
        "damage": 60,
        "turns": 0
    },
    {
        "energy": 45,
        "nameid": "DYNAMAX_CANNON",
        "buffChance": 0,
        "buffSelf": false,
        "buffEffect": "",
        "name": "Dynamax Cannon",
        "type": "dragon",
        "damage": 80,
        "turns": 0
    },
    {
        "energy": 45,
        "nameid": "DYNAMIC_PUNCH",
        "buffChance": 0,
        "buffSelf": false,
        "buffEffect": "",
        "name": "Dynamic Punch",
        "type": "fighting",
        "damage": 90,
        "turns": 0
    },
    {
        "energy": 65,
        "nameid": "EARTHQUAKE",
        "buffChance": 0,
        "buffSelf": false,
        "buffEffect": "",
        "name": "Earthquake",
        "type": "ground",
        "damage": 110,
        "turns": 0
    },
    {
        "energy": 55,
        "nameid": "EARTH_POWER",
        "buffChance": ".1",
        "buffSelf": false,
        "buffEffect": " -1 DEF",
        "name": "Earth Power",
        "type": "ground",
        "damage": 90,
        "turns": 0
    },
    {
        "energy": 9,
        "nameid": "EMBER",
        "buffChance": 0,
        "buffSelf": false,
        "buffEffect": "",
        "name": "Ember",
        "type": "fire",
        "damage": 4,
        "turns": 2
    },
    {
        "energy": 55,
        "nameid": "ENERGY_BALL",
        "buffChance": ".1",
        "buffSelf": false,
        "buffEffect": " -1 DEF",
        "name": "Energy Ball",
        "type": "grass",
        "damage": 90,
        "turns": 0
    },
    {
        "energy": 10,
        "nameid": "EXTRASENSORY",
        "buffChance": 0,
        "buffSelf": false,
        "buffEffect": "",
        "name": "Extrasensory",
        "type": "psychic",
        "damage": 8,
        "turns": 3
    },
    {
        "energy": 9,
        "nameid": "FAIRY_WIND",
        "buffChance": 0,
        "buffSelf": false,
        "buffEffect": "",
        "name": "Fairy Wind",
        "type": "fairy",
        "damage": 4,
        "turns": 2
    },
    {
        "energy": 50,
        "nameid": "FEATHER_DANCE",
        "buffChance": "1",
        "buffSelf": false,
        "buffEffect": "-2 ATK",
        "name": "Feather Dance",
        "type": "flying",
        "damage": 35,
        "turns": 0
    },
    {
        "energy": 6,
        "nameid": "FEINT_ATTACK",
        "buffChance": 0,
        "buffSelf": false,
        "buffEffect": "",
        "name": "Feint Attack",
        "type": "dark",
        "damage": 6,
        "turns": 2
    },
    {
        "energy": 35,
        "nameid": "FELL_STINGER",
        "buffChance": "1",
        "buffSelf": true,
        "buffEffect": "+1 ATK",
        "name": "Fell Stinger",
        "type": "bug",
        "damage": 20,
        "turns": 0
    },
    {
        "energy": 80,
        "nameid": "FIRE_BLAST",
        "buffChance": 0,
        "buffSelf": false,
        "buffEffect": "",
        "name": "Fire Blast",
        "type": "fire",
        "damage": 140,
        "turns": 0
    },
    {
        "energy": 6,
        "nameid": "FIRE_FANG",
        "buffChance": 0,
        "buffSelf": false,
        "buffEffect": "",
        "name": "Fire Fang",
        "type": "fire",
        "damage": 8,
        "turns": 2
    },
    {
        "energy": 40,
        "nameid": "FIRE_PUNCH",
        "buffChance": 0,
        "buffSelf": false,
        "buffEffect": "",
        "name": "Fire Punch",
        "type": "fire",
        "damage": 60,
        "turns": 0
    },
    {
        "energy": 10,
        "nameid": "FIRE_SPIN",
        "buffChance": 0,
        "buffSelf": false,
        "buffEffect": "",
        "name": "Fire Spin",
        "type": "fire",
        "damage": 11,
        "turns": 3
    },
    {
        "energy": 55,
        "nameid": "FLAMETHROWER",
        "buffChance": 0,
        "buffSelf": false,
        "buffEffect": "",
        "name": "Flamethrower",
        "type": "fire",
        "damage": 90,
        "turns": 0
    },
    {
        "energy": 55,
        "nameid": "FLAME_BURST",
        "buffChance": 0,
        "buffSelf": false,
        "buffEffect": "",
        "name": "Flame Burst",
        "type": "fire",
        "damage": 70,
        "turns": 0
    },
    {
        "energy": 50,
        "nameid": "FLAME_CHARGE",
        "buffChance": "1",
        "buffSelf": true,
        "buffEffect": "+1 ATK",
        "name": "Flame Charge",
        "type": "fire",
        "damage": 65,
        "turns": 0
    },
    {
        "energy": 45,
        "nameid": "FLAME_WHEEL",
        "buffChance": 0,
        "buffSelf": false,
        "buffEffect": "",
        "name": "Flame Wheel",
        "type": "fire",
        "damage": 80,
        "turns": 0
    },
    {
        "energy": 70,
        "nameid": "FLASH_CANNON",
        "buffChance": 0,
        "buffSelf": false,
        "buffEffect": "",
        "name": "Flash Cannon",
        "type": "steel",
        "damage": 110,
        "turns": 0
    },
    {
        "energy": 35,
        "nameid": "FLOWER_TRICK",
        "buffChance": "1",
        "buffSelf": true,
        "buffEffect": "+1 ATK",
        "name": "Flower Trick",
        "type": "grass",
        "damage": 30,
        "turns": 0
    },
    {
        "energy": 45,
        "nameid": "FLY",
        "buffChance": 0,
        "buffSelf": false,
        "buffEffect": "",
        "name": "Fly",
        "type": "flying",
        "damage": 80,
        "turns": 0
    },
    {
        "energy": 40,
        "nameid": "FLYING_PRESS",
        "buffChance": 0,
        "buffSelf": false,
        "buffEffect": "",
        "name": "Flying Press",
        "type": "fighting",
        "damage": 90,
        "turns": 0
    },
    {
        "energy": 75,
        "nameid": "FOCUS_BLAST",
        "buffChance": 0,
        "buffSelf": false,
        "buffEffect": "",
        "name": "Focus Blast",
        "type": "fighting",
        "damage": 150,
        "turns": 0
    },
    {
        "energy": 10,
        "nameid": "FORCE_PALM",
        "buffChance": 0,
        "buffSelf": false,
        "buffEffect": "",
        "name": "Force Palm",
        "type": "fighting",
        "damage": 13,
        "turns": 3
    },
    {
        "energy": 40,
        "nameid": "FOUL_PLAY",
        "buffChance": 0,
        "buffSelf": false,
        "buffEffect": "",
        "name": "Foul Play",
        "type": "dark",
        "damage": 65,
        "turns": 0
    },
    {
        "energy": 60,
        "nameid": "FREEZE_SHOCK",
        "buffChance": ".3",
        "buffSelf": false,
        "buffEffect": "-1 ATK",
        "name": "Freeze Shock",
        "type": "ice",
        "damage": 120,
        "turns": 0
    },
    {
        "energy": 45,
        "nameid": "FRENZY_PLANT",
        "buffChance": 0,
        "buffSelf": false,
        "buffEffect": "",
        "name": "Frenzy Plant",
        "type": "grass",
        "damage": 100,
        "turns": 0
    },
    {
        "energy": 5,
        "nameid": "FROST_BREATH",
        "buffChance": 0,
        "buffSelf": false,
        "buffEffect": "",
        "name": "Frost Breath",
        "type": "ice",
        "damage": 7,
        "turns": 2
    },
    {
        "energy": 70,
        "nameid": "FRUSTRATION",
        "buffChance": 0,
        "buffSelf": false,
        "buffEffect": "",
        "name": "Frustration",
        "type": "normal",
        "damage": 10,
        "turns": 0
    },
    {
        "energy": 4,
        "nameid": "FURY_CUTTER",
        "buffChance": 0,
        "buffSelf": false,
        "buffEffect": "",
        "name": "Fury Cutter",
        "type": "bug",
        "damage": 3,
        "turns": 1
    },
    {
        "energy": 45,
        "nameid": "FUSION_BOLT",
        "buffChance": 0,
        "buffSelf": false,
        "buffEffect": "",
        "name": "Fusion Bolt",
        "type": "electric",
        "damage": 90,
        "turns": 0
    },
    {
        "energy": 45,
        "nameid": "FUSION_FLARE",
        "buffChance": 0,
        "buffSelf": false,
        "buffEffect": "",
        "name": "Fusion Flare",
        "type": "fire",
        "damage": 90,
        "turns": 0
    },
    {
        "energy": 65,
        "nameid": "FUTURE_SIGHT",
        "buffChance": 0,
        "buffSelf": false,
        "buffEffect": "",
        "name": "Future Sight",
        "type": "psychic",
        "damage": 110,
        "turns": 0
    },
    {
        "energy": 13,
        "nameid": "GEOMANCY",
        "buffChance": 0,
        "buffSelf": false,
        "buffEffect": "",
        "name": "Geomancy",
        "type": "fairy",
        "damage": 8,
        "turns": 3
    },
    {
        "energy": 80,
        "nameid": "GIGA_DRAIN",
        "buffChance": 0,
        "buffSelf": false,
        "buffEffect": "",
        "name": "Giga Drain",
        "type": "grass",
        "damage": 50,
        "turns": 0
    },
    {
        "energy": 80,
        "nameid": "GIGA_IMPACT",
        "buffChance": 0,
        "buffSelf": false,
        "buffEffect": "",
        "name": "Giga Impact",
        "type": "normal",
        "damage": 150,
        "turns": 0
    },
    {
        "energy": 40,
        "nameid": "GLACIATE",
        "buffChance": "1",
        "buffSelf": false,
        "buffEffect": "-1 ATK",
        "name": "Glaciate",
        "type": "ice",
        "damage": 60,
        "turns": 0
    },
    {
        "energy": 50,
        "nameid": "GRASS_KNOT",
        "buffChance": 0,
        "buffSelf": false,
        "buffEffect": "",
        "name": "Grass Knot",
        "type": "grass",
        "damage": 90,
        "turns": 0
    },
    {
        "energy": 75,
        "nameid": "GUNK_SHOT",
        "buffChance": 0,
        "buffSelf": false,
        "buffEffect": "",
        "name": "Gunk Shot",
        "type": "poison",
        "damage": 130,
        "turns": 0
    },
    {
        "energy": 12,
        "nameid": "GUST",
        "buffChance": 0,
        "buffSelf": false,
        "buffEffect": "",
        "name": "Gust",
        "type": "flying",
        "damage": 16,
        "turns": 4
    },
    {
        "energy": 50,
        "nameid": "GYRO_BALL",
        "buffChance": 0,
        "buffSelf": false,
        "buffEffect": "",
        "name": "Gyro Ball",
        "type": "steel",
        "damage": 80,
        "turns": 0
    },
    {
        "energy": 40,
        "nameid": "HEART_STAMP",
        "buffChance": 0,
        "buffSelf": false,
        "buffEffect": "",
        "name": "Heart Stamp",
        "type": "psychic",
        "damage": 40,
        "turns": 0
    },
    {
        "energy": 75,
        "nameid": "HEAT_WAVE",
        "buffChance": 0,
        "buffSelf": false,
        "buffEffect": "",
        "name": "Heat Wave",
        "type": "fire",
        "damage": 95,
        "turns": 0
    },
    {
        "energy": 50,
        "nameid": "HEAVY_SLAM",
        "buffChance": 0,
        "buffSelf": false,
        "buffEffect": "",
        "name": "Heavy Slam",
        "type": "steel",
        "damage": 70,
        "turns": 0
    },
    {
        "energy": 13,
        "nameid": "HEX",
        "buffChance": 0,
        "buffSelf": false,
        "buffEffect": "",
        "name": "Hex",
        "type": "ghost",
        "damage": 7,
        "turns": 3
    },
    {
        "energy": 8,
        "nameid": "HIDDEN_POWER_BUG",
        "buffChance": 0,
        "buffSelf": false,
        "buffEffect": "",
        "name": "Hidden Power (Bug)",
        "type": "bug",
        "damage": 9,
        "turns": 3
    },
    {
        "energy": 8,
        "nameid": "HIDDEN_POWER_DARK",
        "buffChance": 0,
        "buffSelf": false,
        "buffEffect": "",
        "name": "Hidden Power (Dark)",
        "type": "dark",
        "damage": 9,
        "turns": 3
    },
    {
        "energy": 8,
        "nameid": "HIDDEN_POWER_DRAGON",
        "buffChance": 0,
        "buffSelf": false,
        "buffEffect": "",
        "name": "Hidden Power (Dragon)",
        "type": "dragon",
        "damage": 9,
        "turns": 3
    },
    {
        "energy": 8,
        "nameid": "HIDDEN_POWER_ELECTRIC",
        "buffChance": 0,
        "buffSelf": false,
        "buffEffect": "",
        "name": "Hidden Power (Electric)",
        "type": "electric",
        "damage": 9,
        "turns": 3
    },
    {
        "energy": 8,
        "nameid": "HIDDEN_POWER_FIGHTING",
        "buffChance": 0,
        "buffSelf": false,
        "buffEffect": "",
        "name": "Hidden Power (Fighting)",
        "type": "fighting",
        "damage": 9,
        "turns": 3
    },
    {
        "energy": 8,
        "nameid": "HIDDEN_POWER_FIRE",
        "buffChance": 0,
        "buffSelf": false,
        "buffEffect": "",
        "name": "Hidden Power (Fire)",
        "type": "fire",
        "damage": 9,
        "turns": 3
    },
    {
        "energy": 8,
        "nameid": "HIDDEN_POWER_FLYING",
        "buffChance": 0,
        "buffSelf": false,
        "buffEffect": "",
        "name": "Hidden Power (Flying)",
        "type": "flying",
        "damage": 9,
        "turns": 3
    },
    {
        "energy": 8,
        "nameid": "HIDDEN_POWER_GHOST",
        "buffChance": 0,
        "buffSelf": false,
        "buffEffect": "",
        "name": "Hidden Power (Ghost)",
        "type": "ghost",
        "damage": 9,
        "turns": 3
    },
    {
        "energy": 8,
        "nameid": "HIDDEN_POWER_GRASS",
        "buffChance": 0,
        "buffSelf": false,
        "buffEffect": "",
        "name": "Hidden Power (Grass)",
        "type": "grass",
        "damage": 9,
        "turns": 3
    },
    {
        "energy": 8,
        "nameid": "HIDDEN_POWER_GROUND",
        "buffChance": 0,
        "buffSelf": false,
        "buffEffect": "",
        "name": "Hidden Power (Ground)",
        "type": "ground",
        "damage": 9,
        "turns": 3
    },
    {
        "energy": 8,
        "nameid": "HIDDEN_POWER_ICE",
        "buffChance": 0,
        "buffSelf": false,
        "buffEffect": "",
        "name": "Hidden Power (Ice)",
        "type": "ice",
        "damage": 9,
        "turns": 3
    },
    {
        "energy": 8,
        "nameid": "HIDDEN_POWER_POISON",
        "buffChance": 0,
        "buffSelf": false,
        "buffEffect": "",
        "name": "Hidden Power (Poison)",
        "type": "poison",
        "damage": 9,
        "turns": 3
    },
    {
        "energy": 8,
        "nameid": "HIDDEN_POWER_PSYCHIC",
        "buffChance": 0,
        "buffSelf": false,
        "buffEffect": "",
        "name": "Hidden Power (Psychic)",
        "type": "psychic",
        "damage": 9,
        "turns": 3
    },
    {
        "energy": 8,
        "nameid": "HIDDEN_POWER_ROCK",
        "buffChance": 0,
        "buffSelf": false,
        "buffEffect": "",
        "name": "Hidden Power (Rock)",
        "type": "rock",
        "damage": 9,
        "turns": 3
    },
    {
        "energy": 8,
        "nameid": "HIDDEN_POWER_STEEL",
        "buffChance": 0,
        "buffSelf": false,
        "buffEffect": "",
        "name": "Hidden Power (Steel)",
        "type": "steel",
        "damage": 9,
        "turns": 3
    },
    {
        "energy": 8,
        "nameid": "HIDDEN_POWER_WATER",
        "buffChance": 0,
        "buffSelf": false,
        "buffEffect": "",
        "name": "Hidden Power (Water)",
        "type": "water",
        "damage": 9,
        "turns": 3
    },
    {
        "energy": 60,
        "nameid": "HIGH_HORSEPOWER",
        "buffChance": 0,
        "buffSelf": false,
        "buffEffect": "",
        "name": "High Horsepower",
        "type": "ground",
        "damage": 100,
        "turns": 0
    },
    {
        "energy": 55,
        "nameid": "HIGH_JUMP_KICK",
        "buffChance": ".1",
        "buffSelf": true,
        "buffEffect": " -4 DEF",
        "name": "High Jump Kick",
        "type": "fighting",
        "damage": 110,
        "turns": 0
    },
    {
        "energy": 35,
        "nameid": "HORN_ATTACK",
        "buffChance": 0,
        "buffSelf": false,
        "buffEffect": "",
        "name": "Horn Attack",
        "type": "normal",
        "damage": 40,
        "turns": 0
    },
    {
        "energy": 65,
        "nameid": "HURRICANE",
        "buffChance": 0,
        "buffSelf": false,
        "buffEffect": "",
        "name": "Hurricane",
        "type": "flying",
        "damage": 110,
        "turns": 0
    },
    {
        "energy": 40,
        "nameid": "HYDRO_CANNON",
        "buffChance": 0,
        "buffSelf": false,
        "buffEffect": "",
        "name": "Hydro Cannon",
        "type": "water",
        "damage": 80,
        "turns": 0
    },
    {
        "energy": 75,
        "nameid": "HYDRO_PUMP",
        "buffChance": 0,
        "buffSelf": false,
        "buffEffect": "",
        "name": "Hydro Pump",
        "type": "water",
        "damage": 130,
        "turns": 0
    },
    {
        "energy": 80,
        "nameid": "HYDRO_PUMP_BLASTOISE",
        "buffChance": 0,
        "buffSelf": false,
        "buffEffect": "",
        "name": "Hydro Pump Blastoise",
        "type": "water",
        "damage": 90,
        "turns": 0
    },
    {
        "energy": 80,
        "nameid": "HYPER_BEAM",
        "buffChance": 0,
        "buffSelf": false,
        "buffEffect": "",
        "name": "Hyper Beam",
        "type": "normal",
        "damage": 150,
        "turns": 0
    },
    {
        "energy": 50,
        "nameid": "HYPER_FANG",
        "buffChance": 0,
        "buffSelf": false,
        "buffEffect": "",
        "name": "Hyper Fang",
        "type": "normal",
        "damage": 80,
        "turns": 0
    },
    {
        "energy": 55,
        "nameid": "ICE_BEAM",
        "buffChance": 0,
        "buffSelf": false,
        "buffEffect": "",
        "name": "Ice Beam",
        "type": "ice",
        "damage": 90,
        "turns": 0
    },
    {
        "energy": 60,
        "nameid": "ICE_BURN",
        "buffChance": ".3",
        "buffSelf": false,
        "buffEffect": " -1 DEF",
        "name": "Ice Burn",
        "type": "ice",
        "damage": 120,
        "turns": 0
    },
    {
        "energy": 6,
        "nameid": "ICE_FANG",
        "buffChance": 0,
        "buffSelf": false,
        "buffEffect": "",
        "name": "Ice Fang",
        "type": "ice",
        "damage": 8,
        "turns": 2
    },
    {
        "energy": 40,
        "nameid": "ICE_PUNCH",
        "buffChance": 0,
        "buffSelf": false,
        "buffEffect": "",
        "name": "Ice Punch",
        "type": "ice",
        "damage": 60,
        "turns": 0
    },
    {
        "energy": 10,
        "nameid": "ICE_SHARD",
        "buffChance": 0,
        "buffSelf": false,
        "buffEffect": "",
        "name": "Ice Shard",
        "type": "ice",
        "damage": 9,
        "turns": 3
    },
    {
        "energy": 40,
        "nameid": "ICICLE_SPEAR",
        "buffChance": 0,
        "buffSelf": false,
        "buffEffect": "",
        "name": "Icicle Spear",
        "type": "ice",
        "damage": 70,
        "turns": 0
    },
    {
        "energy": 45,
        "nameid": "ICY_WIND",
        "buffChance": "1",
        "buffSelf": false,
        "buffEffect": "-1 ATK",
        "name": "Icy Wind",
        "type": "ice",
        "damage": 60,
        "turns": 0
    },
    {
        "energy": 20,
        "nameid": "INCINERATE",
        "buffChance": 0,
        "buffSelf": false,
        "buffEffect": "",
        "name": "Incinerate",
        "type": "fire",
        "damage": 20,
        "turns": 5
    },
    {
        "energy": 12,
        "nameid": "INFESTATION",
        "buffChance": 0,
        "buffSelf": false,
        "buffEffect": "",
        "name": "Infestation",
        "type": "bug",
        "damage": 6,
        "turns": 3
    },
    {
        "energy": 50,
        "nameid": "IRON_HEAD",
        "buffChance": 0,
        "buffSelf": false,
        "buffEffect": "",
        "name": "Iron Head",
        "type": "steel",
        "damage": 70,
        "turns": 0
    },
    {
        "energy": 7,
        "nameid": "IRON_TAIL",
        "buffChance": 0,
        "buffSelf": false,
        "buffEffect": "",
        "name": "Iron Tail",
        "type": "steel",
        "damage": 10,
        "turns": 3
    },
    {
        "energy": 9,
        "nameid": "KARATE_CHOP",
        "buffChance": 0,
        "buffSelf": false,
        "buffEffect": "",
        "name": "Karate Chop",
        "type": "fighting",
        "damage": 5,
        "turns": 2
    },
    {
        "energy": 55,
        "nameid": "LAST_RESORT",
        "buffChance": 0,
        "buffSelf": false,
        "buffEffect": "",
        "name": "Last Resort",
        "type": "normal",
        "damage": 90,
        "turns": 0
    },
    {
        "energy": 8,
        "nameid": "LEAFAGE",
        "buffChance": 0,
        "buffSelf": false,
        "buffEffect": "",
        "name": "Leafage",
        "type": "grass",
        "damage": 6,
        "turns": 2
    },
    {
        "energy": 35,
        "nameid": "LEAF_BLADE",
        "buffChance": 0,
        "buffSelf": false,
        "buffEffect": "",
        "name": "Leaf Blade",
        "type": "grass",
        "damage": 70,
        "turns": 0
    },
    {
        "energy": 55,
        "nameid": "LEAF_STORM",
        "buffChance": "1",
        "buffSelf": true,
        "buffEffect": "-2 ATK",
        "name": "Leaf Storm",
        "type": "grass",
        "damage": 130,
        "turns": 0
    },
    {
        "energy": 40,
        "nameid": "LEAF_TORNADO",
        "buffChance": ".5",
        "buffSelf": false,
        "buffEffect": "-2 ATK",
        "name": "Leaf Tornado",
        "type": "grass",
        "damage": 45,
        "turns": 0
    },
    {
        "energy": 3,
        "nameid": "LICK",
        "buffChance": 0,
        "buffSelf": false,
        "buffEffect": "",
        "name": "Lick",
        "type": "ghost",
        "damage": 3,
        "turns": 1
    },
    {
        "energy": 45,
        "nameid": "LIQUIDATION",
        "buffChance": "0.3",
        "buffSelf": false,
        "buffEffect": " -1 DEF",
        "name": "Liquidation",
        "type": "water",
        "damage": 70,
        "turns": 0
    },
    {
        "energy": 5,
        "nameid": "LOCK_ON",
        "buffChance": 0,
        "buffSelf": false,
        "buffEffect": "",
        "name": "Lock On",
        "type": "normal",
        "damage": 1,
        "turns": 1
    },
    {
        "energy": 5,
        "nameid": "LOW_KICK",
        "buffChance": 0,
        "buffSelf": false,
        "buffEffect": "",
        "name": "Low Kick",
        "type": "fighting",
        "damage": 4,
        "turns": 2
    },
    {
        "energy": 40,
        "nameid": "LOW_SWEEP",
        "buffChance": 0,
        "buffSelf": false,
        "buffEffect": "",
        "name": "Low Sweep",
        "type": "fighting",
        "damage": 40,
        "turns": 0
    },
    {
        "energy": 45,
        "nameid": "LUNGE",
        "buffChance": "1",
        "buffSelf": false,
        "buffEffect": "-1 ATK",
        "name": "Lunge",
        "type": "bug",
        "damage": 60,
        "turns": 0
    },
    {
        "energy": 60,
        "nameid": "LUSTER_PURGE",
        "buffChance": "0.5",
        "buffSelf": false,
        "buffEffect": " -1 DEF",
        "name": "Luster Purge",
        "type": "psychic",
        "damage": 120,
        "turns": 0
    },
    {
        "energy": 10,
        "nameid": "MAGICAL_LEAF",
        "buffChance": 0,
        "buffSelf": false,
        "buffEffect": "",
        "name": "Magical Leaf",
        "type": "grass",
        "damage": 10,
        "turns": 3
    },
    {
        "energy": 40,
        "nameid": "MAGMA_STORM",
        "buffChance": 0,
        "buffSelf": false,
        "buffEffect": "",
        "name": "Magma Storm",
        "type": "fire",
        "damage": 65,
        "turns": 0
    },
    {
        "energy": 45,
        "nameid": "MAGNET_BOMB",
        "buffChance": 0,
        "buffSelf": false,
        "buffEffect": "",
        "name": "Magnet Bomb",
        "type": "steel",
        "damage": 70,
        "turns": 0
    },
    {
        "energy": 55,
        "nameid": "MEGAHORN",
        "buffChance": 0,
        "buffSelf": false,
        "buffEffect": "",
        "name": "Megahorn",
        "type": "bug",
        "damage": 110,
        "turns": 0
    },
    {
        "energy": 55,
        "nameid": "MEGA_DRAIN",
        "buffChance": 0,
        "buffSelf": false,
        "buffEffect": "",
        "name": "Mega Drain",
        "type": "grass",
        "damage": 25,
        "turns": 0
    },
    {
        "energy": 7,
        "nameid": "METAL_CLAW",
        "buffChance": 0,
        "buffSelf": false,
        "buffEffect": "",
        "name": "Metal Claw",
        "type": "steel",
        "damage": 5,
        "turns": 2
    },
    {
        "energy": 8,
        "nameid": "METAL_SOUND",
        "buffChance": 0,
        "buffSelf": false,
        "buffEffect": "",
        "name": "Metal Sound",
        "type": "steel",
        "damage": 5,
        "turns": 2
    },
    {
        "energy": 60,
        "nameid": "METEOR_BEAM",
        "buffChance": "1",
        "buffSelf": true,
        "buffEffect": "+1 ATK",
        "name": "Meteor Beam",
        "type": "rock",
        "damage": 120,
        "turns": 0
    },
    {
        "energy": 45,
        "nameid": "METEOR_MASH",
        "buffChance": 0,
        "buffSelf": false,
        "buffEffect": "",
        "name": "Meteor Mash",
        "type": "steel",
        "damage": 100,
        "turns": 0
    },
    {
        "energy": 35,
        "nameid": "MIND_BLOWN",
        "buffChance": "1",
        "buffSelf": true,
        "buffEffect": " -4 DEF",
        "name": "Mind Blown",
        "type": "fire",
        "damage": 90,
        "turns": 0
    },
    {
        "energy": 55,
        "nameid": "MIRROR_COAT",
        "buffChance": 0,
        "buffSelf": false,
        "buffEffect": "",
        "name": "Mirror Coat",
        "type": "psychic",
        "damage": 60,
        "turns": 0
    },
    {
        "energy": 35,
        "nameid": "MIRROR_SHOT",
        "buffChance": ".3",
        "buffSelf": false,
        "buffEffect": "-1 ATK",
        "name": "Mirror Shot",
        "type": "steel",
        "damage": 35,
        "turns": 0
    },
    {
        "energy": 60,
        "nameid": "MIST_BALL",
        "buffChance": "0.5",
        "buffSelf": false,
        "buffEffect": "-1 ATK",
        "name": "Mist Ball",
        "type": "psychic",
        "damage": 120,
        "turns": 0
    },
    {
        "energy": 60,
        "nameid": "MOONBLAST",
        "buffChance": ".1",
        "buffSelf": false,
        "buffEffect": "-1 ATK",
        "name": "Moonblast",
        "type": "fairy",
        "damage": 110,
        "turns": 0
    },
    {
        "energy": 65,
        "nameid": "MOONGEIST_BEAM",
        "buffChance": 0,
        "buffSelf": false,
        "buffEffect": "",
        "name": "Moongeist Beam",
        "type": "ghost",
        "damage": 135,
        "turns": 0
    },
    {
        "energy": 35,
        "nameid": "MUDDY_WATER",
        "buffChance": ".3",
        "buffSelf": false,
        "buffEffect": "-1 ATK",
        "name": "Muddy Water",
        "type": "water",
        "damage": 35,
        "turns": 0
    },
    {
        "energy": 40,
        "nameid": "MUD_BOMB",
        "buffChance": 0,
        "buffSelf": false,
        "buffEffect": "",
        "name": "Mud Bomb",
        "type": "ground",
        "damage": 60,
        "turns": 0
    },
    {
        "energy": 8,
        "nameid": "MUD_SHOT",
        "buffChance": 0,
        "buffSelf": false,
        "buffEffect": "",
        "name": "Mud Shot",
        "type": "ground",
        "damage": 4,
        "turns": 2
    },
    {
        "energy": 10,
        "nameid": "MUD_SLAP",
        "buffChance": 0,
        "buffSelf": false,
        "buffEffect": "",
        "name": "Mud Slap",
        "type": "ground",
        "damage": 12,
        "turns": 3
    },
    {
        "energy": 45,
        "nameid": "MYSTICAL_FIRE",
        "buffChance": "1",
        "buffSelf": false,
        "buffEffect": "-1 ATK",
        "name": "Mystical Fire",
        "type": "fire",
        "damage": 60,
        "turns": 0
    },
    {
        "energy": 50,
        "nameid": "NATURES_MADNESS",
        "buffChance": "1",
        "buffSelf": false,
        "buffEffect": " -1 DEF",
        "name": "Nature's Madness",
        "type": "fairy",
        "damage": 80,
        "turns": 0
    },
    {
        "energy": 45,
        "nameid": "NIGHT_SHADE",
        "buffChance": 0,
        "buffSelf": false,
        "buffEffect": "",
        "name": "Night Shade",
        "type": "ghost",
        "damage": 70,
        "turns": 0
    },
    {
        "energy": 35,
        "nameid": "NIGHT_SLASH",
        "buffChance": ".125",
        "buffSelf": true,
        "buffEffect": "+2 ATK",
        "name": "Night Slash",
        "type": "dark",
        "damage": 50,
        "turns": 0
    },
    {
        "energy": 50,
        "nameid": "OBLIVION_WING",
        "buffChance": "1",
        "buffSelf": true,
        "buffEffect": " +1 DEF",
        "name": "Oblivion Wing",
        "type": "flying",
        "damage": 85,
        "turns": 0
    },
    {
        "energy": 40,
        "nameid": "OBSTRUCT",
        "buffChance": "1",
        "buffSelf": false,
        "buffEffect": " +1 DEF",
        "name": "Obstruct",
        "type": "dark",
        "damage": 15,
        "turns": 0
    },
    {
        "energy": 50,
        "nameid": "OCTAZOOKA",
        "buffChance": "0.5",
        "buffSelf": false,
        "buffEffect": "-2 ATK",
        "name": "Octazooka",
        "type": "water",
        "damage": 50,
        "turns": 0
    },
    {
        "energy": 45,
        "nameid": "OMINOUS_WIND",
        "buffChance": ".1",
        "buffSelf": true,
        "buffEffect": "+1 ATK +1 DEF",
        "name": "Ominous Wind",
        "type": "ghost",
        "damage": 45,
        "turns": 0
    },
    {
        "energy": 60,
        "nameid": "ORIGIN_PULSE",
        "buffChance": 0,
        "buffSelf": false,
        "buffEffect": "",
        "name": "Origin Pulse",
        "type": "water",
        "damage": 130,
        "turns": 0
    },
    {
        "energy": 60,
        "nameid": "OUTRAGE",
        "buffChance": 0,
        "buffSelf": false,
        "buffEffect": "",
        "name": "Outrage",
        "type": "dragon",
        "damage": 110,
        "turns": 0
    },
    {
        "energy": 55,
        "nameid": "OVERHEAT",
        "buffChance": "1",
        "buffSelf": true,
        "buffEffect": "-2 ATK",
        "name": "Overheat",
        "type": "fire",
        "damage": 130,
        "turns": 0
    },
    {
        "energy": 50,
        "nameid": "PARABOLIC_CHARGE",
        "buffChance": "1",
        "buffSelf": true,
        "buffEffect": " +1 DEF",
        "name": "Parabolic Charge",
        "type": "electric",
        "damage": 70,
        "turns": 0
    },
    {
        "energy": 60,
        "nameid": "PAYBACK",
        "buffChance": 0,
        "buffSelf": false,
        "buffEffect": "",
        "name": "Payback",
        "type": "dark",
        "damage": 110,
        "turns": 0
    },
    {
        "energy": 8,
        "nameid": "PECK",
        "buffChance": 0,
        "buffSelf": false,
        "buffEffect": "",
        "name": "Peck",
        "type": "flying",
        "damage": 6,
        "turns": 2
    },
    {
        "energy": 65,
        "nameid": "PETAL_BLIZZARD",
        "buffChance": 0,
        "buffSelf": false,
        "buffEffect": "",
        "name": "Petal Blizzard",
        "type": "grass",
        "damage": 110,
        "turns": 0
    },
    {
        "energy": 60,
        "nameid": "PLAY_ROUGH",
        "buffChance": 0,
        "buffSelf": false,
        "buffEffect": "",
        "name": "Play Rough",
        "type": "fairy",
        "damage": 90,
        "turns": 0
    },
    {
        "energy": 40,
        "nameid": "POISON_FANG",
        "buffChance": "1",
        "buffSelf": false,
        "buffEffect": " -1 DEF",
        "name": "Poison Fang",
        "type": "poison",
        "damage": 45,
        "turns": 0
    },
    {
        "energy": 7,
        "nameid": "POISON_JAB",
        "buffChance": 0,
        "buffSelf": false,
        "buffEffect": "",
        "name": "Poison Jab",
        "type": "poison",
        "damage": 7,
        "turns": 2
    },
    {
        "energy": 9,
        "nameid": "POISON_STING",
        "buffChance": 0,
        "buffSelf": false,
        "buffEffect": "",
        "name": "Poison Sting",
        "type": "poison",
        "damage": 4,
        "turns": 2
    },
    {
        "energy": 75,
        "nameid": "POLTERGEIST",
        "buffChance": 0,
        "buffSelf": false,
        "buffEffect": "",
        "name": "Poltergeist",
        "type": "ghost",
        "damage": 150,
        "turns": 0
    },
    {
        "energy": 4,
        "nameid": "POUND",
        "buffChance": 0,
        "buffSelf": false,
        "buffEffect": "",
        "name": "Pound",
        "type": "normal",
        "damage": 4,
        "turns": 2
    },
    {
        "energy": 8,
        "nameid": "POWDER_SNOW",
        "buffChance": 0,
        "buffSelf": false,
        "buffEffect": "",
        "name": "Powder Snow",
        "type": "ice",
        "damage": 6,
        "turns": 2
    },
    {
        "energy": 50,
        "nameid": "POWER_GEM",
        "buffChance": 0,
        "buffSelf": false,
        "buffEffect": "",
        "name": "Power Gem",
        "type": "rock",
        "damage": 85,
        "turns": 0
    },
    {
        "energy": 35,
        "nameid": "POWER_UP_PUNCH",
        "buffChance": "1",
        "buffSelf": true,
        "buffEffect": "+1 ATK",
        "name": "Power-Up Punch",
        "type": "fighting",
        "damage": 20,
        "turns": 0
    },
    {
        "energy": 50,
        "nameid": "POWER_WHIP",
        "buffChance": 0,
        "buffSelf": false,
        "buffEffect": "",
        "name": "Power Whip",
        "type": "grass",
        "damage": 90,
        "turns": 0
    },
    {
        "energy": 60,
        "nameid": "PRECIPICE_BLADES",
        "buffChance": 0,
        "buffSelf": false,
        "buffEffect": "",
        "name": "Precipice Blades",
        "type": "ground",
        "damage": 130,
        "turns": 0
    },
    {
        "energy": 12,
        "nameid": "PRESENT",
        "buffChance": 0,
        "buffSelf": false,
        "buffEffect": "",
        "name": "Present",
        "type": "normal",
        "damage": 3,
        "turns": 3
    },
    {
        "energy": 60,
        "nameid": "PSYBEAM",
        "buffChance": 0,
        "buffSelf": false,
        "buffEffect": "",
        "name": "Psybeam",
        "type": "psychic",
        "damage": 70,
        "turns": 0
    },
    {
        "energy": 55,
        "nameid": "PSYCHIC",
        "buffChance": ".1",
        "buffSelf": false,
        "buffEffect": " -1 DEF",
        "name": "Psychic",
        "type": "psychic",
        "damage": 75,
        "turns": 0
    },
    {
        "energy": 35,
        "nameid": "PSYCHIC_FANGS",
        "buffChance": "1",
        "buffSelf": false,
        "buffEffect": " -1 DEF",
        "name": "Psychic Fangs",
        "type": "psychic",
        "damage": 40,
        "turns": 0
    },
    {
        "energy": 35,
        "nameid": "PSYCHO_BOOST",
        "buffChance": "1",
        "buffSelf": true,
        "buffEffect": "-2 ATK",
        "name": "Psycho Boost",
        "type": "psychic",
        "damage": 70,
        "turns": 0
    },
    {
        "energy": 9,
        "nameid": "PSYCHO_CUT",
        "buffChance": 0,
        "buffSelf": false,
        "buffEffect": "",
        "name": "Psycho Cut",
        "type": "psychic",
        "damage": 3,
        "turns": 2
    },
    {
        "energy": 40,
        "nameid": "PSYSHOCK",
        "buffChance": 0,
        "buffSelf": false,
        "buffEffect": "",
        "name": "Psyshock",
        "type": "psychic",
        "damage": 70,
        "turns": 0
    },
    {
        "energy": 45,
        "nameid": "PSYSTRIKE",
        "buffChance": 0,
        "buffSelf": false,
        "buffEffect": "",
        "name": "Psystrike",
        "type": "psychic",
        "damage": 90,
        "turns": 0
    },
    {
        "energy": 4,
        "nameid": "PSYWAVE",
        "buffChance": 0,
        "buffSelf": false,
        "buffEffect": "",
        "name": "Psywave",
        "type": "psychic",
        "damage": 3,
        "turns": 1
    },
    {
        "energy": 8,
        "nameid": "QUICK_ATTACK",
        "buffChance": 0,
        "buffSelf": false,
        "buffEffect": "",
        "name": "Quick Attack",
        "type": "normal",
        "damage": 5,
        "turns": 2
    },
    {
        "energy": 35,
        "nameid": "RAGE_FIST",
        "buffChance": "1",
        "buffSelf": true,
        "buffEffect": "+1 ATK",
        "name": "Rage Fist",
        "type": "ghost",
        "damage": 50,
        "turns": 0
    },
    {
        "energy": 4,
        "nameid": "RAZOR_LEAF",
        "buffChance": 0,
        "buffSelf": false,
        "buffEffect": "",
        "name": "Razor Leaf",
        "type": "grass",
        "damage": 9,
        "turns": 2
    },
    {
        "energy": 35,
        "nameid": "RAZOR_SHELL",
        "buffChance": "0.5",
        "buffSelf": false,
        "buffEffect": " -1 DEF",
        "name": "Razor Shell",
        "type": "water",
        "damage": 35,
        "turns": 0
    },
    {
        "energy": 35,
        "nameid": "REST",
        "buffChance": 0,
        "buffSelf": false,
        "buffEffect": "",
        "name": "Rest",
        "type": "normal",
        "damage": 50,
        "turns": 0
    },
    {
        "energy": 70,
        "nameid": "RETURN",
        "buffChance": 0,
        "buffSelf": false,
        "buffEffect": "",
        "name": "Return",
        "type": "normal",
        "damage": 130,
        "turns": 0
    },
    {
        "energy": 65,
        "nameid": "ROAR_OF_TIME",
        "buffChance": 0,
        "buffSelf": false,
        "buffEffect": "",
        "name": "Roar of Time",
        "type": "dragon",
        "damage": 150,
        "turns": 0
    },
    {
        "energy": 40,
        "nameid": "ROCK_BLAST",
        "buffChance": 0,
        "buffSelf": false,
        "buffEffect": "",
        "name": "Rock Blast",
        "type": "rock",
        "damage": 50,
        "turns": 0
    },
    {
        "energy": 45,
        "nameid": "ROCK_SLIDE",
        "buffChance": 0,
        "buffSelf": false,
        "buffEffect": "",
        "name": "Rock Slide",
        "type": "rock",
        "damage": 75,
        "turns": 0
    },
    {
        "energy": 7,
        "nameid": "ROCK_SMASH",
        "buffChance": 0,
        "buffSelf": false,
        "buffEffect": "",
        "name": "Rock Smash",
        "type": "fighting",
        "damage": 9,
        "turns": 3
    },
    {
        "energy": 5,
        "nameid": "ROCK_THROW",
        "buffChance": 0,
        "buffSelf": false,
        "buffEffect": "",
        "name": "Rock Throw",
        "type": "rock",
        "damage": 8,
        "turns": 2
    },
    {
        "energy": 50,
        "nameid": "ROCK_TOMB",
        "buffChance": "1",
        "buffSelf": false,
        "buffEffect": "-1 ATK",
        "name": "Rock Tomb",
        "type": "rock",
        "damage": 80,
        "turns": 0
    },
    {
        "energy": 50,
        "nameid": "ROCK_WRECKER",
        "buffChance": 0,
        "buffSelf": false,
        "buffEffect": "",
        "name": "Rock Wrecker",
        "type": "rock",
        "damage": 110,
        "turns": 0
    },
    {
        "energy": 13,
        "nameid": "ROLLOUT",
        "buffChance": 0,
        "buffSelf": false,
        "buffEffect": "",
        "name": "Rollout",
        "type": "rock",
        "damage": 7,
        "turns": 3
    },
    {
        "energy": 65,
        "nameid": "SACRED_FIRE",
        "buffChance": "0.5",
        "buffSelf": false,
        "buffEffect": "-1 ATK",
        "name": "Sacred Fire",
        "type": "fire",
        "damage": 130,
        "turns": 0
    },
    {
        "energy": 35,
        "nameid": "SACRED_SWORD",
        "buffChance": 0,
        "buffSelf": false,
        "buffEffect": "",
        "name": "Sacred Sword",
        "type": "fighting",
        "damage": 60,
        "turns": 0
    },
    {
        "energy": 45,
        "nameid": "SANDSEAR_STORM",
        "buffChance": "1",
        "buffSelf": false,
        "buffEffect": "-1 ATK",
        "name": "Sandsear Storm",
        "type": "ground",
        "damage": 60,
        "turns": 0
    },
    {
        "energy": 4,
        "nameid": "SAND_ATTACK",
        "buffChance": 0,
        "buffSelf": false,
        "buffEffect": "",
        "name": "Sand Attack",
        "type": "ground",
        "damage": 2,
        "turns": 1
    },
    {
        "energy": 40,
        "nameid": "SAND_TOMB",
        "buffChance": "1",
        "buffSelf": false,
        "buffEffect": " -1 DEF",
        "name": "Sand Tomb",
        "type": "ground",
        "damage": 25,
        "turns": 0
    },
    {
        "energy": 50,
        "nameid": "SCALD",
        "buffChance": "0.3",
        "buffSelf": false,
        "buffEffect": "-1 ATK",
        "name": "Scald",
        "type": "water",
        "damage": 85,
        "turns": 0
    },
    {
        "energy": 50,
        "nameid": "SCORCHING_SANDS",
        "buffChance": "0.1",
        "buffSelf": false,
        "buffEffect": "-1 ATK",
        "name": "Scorching Sands",
        "type": "ground",
        "damage": 80,
        "turns": 0
    },
    {
        "energy": 2,
        "nameid": "SCRATCH",
        "buffChance": 0,
        "buffSelf": false,
        "buffEffect": "",
        "name": "Scratch",
        "type": "normal",
        "damage": 4,
        "turns": 1
    },
    {
        "energy": 35,
        "nameid": "SECRET_SWORD",
        "buffChance": 0,
        "buffSelf": false,
        "buffEffect": "",
        "name": "Secret Sword",
        "type": "fighting",
        "damage": 70,
        "turns": 0
    },
    {
        "energy": 40,
        "nameid": "SEED_BOMB",
        "buffChance": 0,
        "buffSelf": false,
        "buffEffect": "",
        "name": "Seed Bomb",
        "type": "grass",
        "damage": 55,
        "turns": 0
    },
    {
        "energy": 75,
        "nameid": "SEED_FLARE",
        "buffChance": ".4",
        "buffSelf": false,
        "buffEffect": " -2 DEF",
        "name": "Seed Flare",
        "type": "grass",
        "damage": 130,
        "turns": 0
    },
    {
        "energy": 50,
        "nameid": "SHADOW_BALL",
        "buffChance": 0,
        "buffSelf": false,
        "buffEffect": "",
        "name": "Shadow Ball",
        "type": "ghost",
        "damage": 100,
        "turns": 0
    },
    {
        "energy": 45,
        "nameid": "SHADOW_BONE",
        "buffChance": ".2",
        "buffSelf": false,
        "buffEffect": " -1 DEF",
        "name": "Shadow Bone",
        "type": "ghost",
        "damage": 80,
        "turns": 0
    },
    {
        "energy": 8,
        "nameid": "SHADOW_CLAW",
        "buffChance": 0,
        "buffSelf": false,
        "buffEffect": "",
        "name": "Shadow Claw",
        "type": "ghost",
        "damage": 6,
        "turns": 2
    },
    {
        "energy": 90,
        "nameid": "SHADOW_FORCE",
        "buffChance": 0,
        "buffSelf": false,
        "buffEffect": "",
        "name": "Shadow Force",
        "type": "ghost",
        "damage": 120,
        "turns": 0
    },
    {
        "energy": 35,
        "nameid": "SHADOW_PUNCH",
        "buffChance": 0,
        "buffSelf": false,
        "buffEffect": "",
        "name": "Shadow Punch",
        "type": "ghost",
        "damage": 55,
        "turns": 0
    },
    {
        "energy": 50,
        "nameid": "SHADOW_SNEAK",
        "buffChance": 0,
        "buffSelf": false,
        "buffEffect": "",
        "name": "Shadow Sneak",
        "type": "ghost",
        "damage": 75,
        "turns": 0
    },
    {
        "energy": 55,
        "nameid": "SIGNAL_BEAM",
        "buffChance": ".2",
        "buffSelf": false,
        "buffEffect": "-1 ATK -1 DEF",
        "name": "Signal Beam",
        "type": "bug",
        "damage": 75,
        "turns": 0
    },
    {
        "energy": 45,
        "nameid": "SILVER_WIND",
        "buffChance": ".1",
        "buffSelf": true,
        "buffEffect": "+1 ATK +1 DEF",
        "name": "Silver Wind",
        "type": "bug",
        "damage": 60,
        "turns": 0
    },
    {
        "energy": 75,
        "nameid": "SKULL_BASH",
        "buffChance": "1",
        "buffSelf": true,
        "buffEffect": " +1 DEF",
        "name": "Skull Bash",
        "type": "normal",
        "damage": 130,
        "turns": 0
    },
    {
        "energy": 50,
        "nameid": "SKY_ATTACK",
        "buffChance": 0,
        "buffSelf": false,
        "buffEffect": "",
        "name": "Sky Attack",
        "type": "flying",
        "damage": 75,
        "turns": 0
    },
    {
        "energy": 40,
        "nameid": "SLUDGE",
        "buffChance": 0,
        "buffSelf": false,
        "buffEffect": "",
        "name": "Sludge",
        "type": "poison",
        "damage": 70,
        "turns": 0
    },
    {
        "energy": 50,
        "nameid": "SLUDGE_BOMB",
        "buffChance": 0,
        "buffSelf": false,
        "buffEffect": "",
        "name": "Sludge Bomb",
        "type": "poison",
        "damage": 80,
        "turns": 0
    },
    {
        "energy": 65,
        "nameid": "SLUDGE_WAVE",
        "buffChance": 0,
        "buffSelf": false,
        "buffEffect": "",
        "name": "Sludge Wave",
        "type": "poison",
        "damage": 110,
        "turns": 0
    },
    {
        "energy": 8,
        "nameid": "SMACK_DOWN",
        "buffChance": 0,
        "buffSelf": false,
        "buffEffect": "",
        "name": "Smack Down",
        "type": "rock",
        "damage": 12,
        "turns": 3
    },
    {
        "energy": 13,
        "nameid": "SNARL",
        "buffChance": 0,
        "buffSelf": false,
        "buffEffect": "",
        "name": "Snarl",
        "type": "dark",
        "damage": 5,
        "turns": 3
    },
    {
        "energy": 80,
        "nameid": "SOLAR_BEAM",
        "buffChance": 0,
        "buffSelf": false,
        "buffEffect": "",
        "name": "Solar Beam",
        "type": "grass",
        "damage": 150,
        "turns": 0
    },
    {
        "energy": 55,
        "nameid": "SPACIAL_REND",
        "buffChance": 0,
        "buffSelf": false,
        "buffEffect": "",
        "name": "Spacial Rend",
        "type": "dragon",
        "damage": 95,
        "turns": 0
    },
    {
        "energy": 7,
        "nameid": "SPARK",
        "buffChance": 0,
        "buffSelf": false,
        "buffEffect": "",
        "name": "Spark",
        "type": "electric",
        "damage": 5,
        "turns": 2
    },
    {
        "energy": 45,
        "nameid": "SPARKLING_ARIA",
        "buffChance": 0,
        "buffSelf": false,
        "buffEffect": "",
        "name": "Sparkling Aria",
        "type": "water",
        "damage": 80,
        "turns": 0
    },
    {
        "energy": 40,
        "nameid": "SPIRIT_SHACKLE",
        "buffChance": ".33",
        "buffSelf": false,
        "buffEffect": " -1 DEF",
        "name": "Spirit Shackle",
        "type": "ghost",
        "damage": 50,
        "turns": 0
    },
    {
        "energy": 12,
        "nameid": "SPLASH",
        "buffChance": 0,
        "buffSelf": false,
        "buffEffect": "",
        "name": "Splash",
        "type": "water",
        "damage": 0,
        "turns": 4
    },
    {
        "energy": 45,
        "nameid": "SPRINGTIDE_STORM",
        "buffChance": "1",
        "buffSelf": false,
        "buffEffect": "-1 ATK",
        "name": "Springtide Storm (Speculative)",
        "type": "fairy",
        "damage": 60,
        "turns": 0
    },
    {
        "energy": 5,
        "nameid": "STEEL_WING",
        "buffChance": 0,
        "buffSelf": false,
        "buffEffect": "",
        "name": "Steel Wing",
        "type": "steel",
        "damage": 7,
        "turns": 2
    },
    {
        "energy": 40,
        "nameid": "STOMP",
        "buffChance": 0,
        "buffSelf": false,
        "buffEffect": "",
        "name": "Stomp",
        "type": "normal",
        "damage": 55,
        "turns": 0
    },
    {
        "energy": 55,
        "nameid": "STONE_EDGE",
        "buffChance": 0,
        "buffSelf": false,
        "buffEffect": "",
        "name": "Stone Edge",
        "type": "rock",
        "damage": 100,
        "turns": 0
    },
    {
        "energy": 100,
        "nameid": "STRUGGLE",
        "buffChance": 0,
        "buffSelf": false,
        "buffEffect": "",
        "name": "Struggle",
        "type": "normal",
        "damage": 35,
        "turns": 0
    },
    {
        "energy": 8,
        "nameid": "STRUGGLE_BUG",
        "buffChance": 0,
        "buffSelf": false,
        "buffEffect": "",
        "name": "Struggle Bug",
        "type": "bug",
        "damage": 9,
        "turns": 3
    },
    {
        "energy": 50,
        "nameid": "SUBMISSION",
        "buffChance": 0,
        "buffSelf": false,
        "buffEffect": "",
        "name": "Submission",
        "type": "fighting",
        "damage": 60,
        "turns": 0
    },
    {
        "energy": 7,
        "nameid": "SUCKER_PUNCH",
        "buffChance": 0,
        "buffSelf": false,
        "buffEffect": "",
        "name": "Sucker Punch",
        "type": "dark",
        "damage": 8,
        "turns": 2
    },
    {
        "energy": 65,
        "nameid": "SUNSTEEL_STRIKE",
        "buffChance": 0,
        "buffSelf": false,
        "buffEffect": "",
        "name": "Sunsteel Strike",
        "type": "steel",
        "damage": 135,
        "turns": 0
    },
    {
        "energy": 40,
        "nameid": "SUPER_POWER",
        "buffChance": "1",
        "buffSelf": true,
        "buffEffect": "-1 ATK -1 DEF",
        "name": "Superpower",
        "type": "fighting",
        "damage": 85,
        "turns": 0
    },
    {
        "energy": 45,
        "nameid": "SURF",
        "buffChance": 0,
        "buffSelf": false,
        "buffEffect": "",
        "name": "Surf",
        "type": "water",
        "damage": 75,
        "turns": 0
    },
    {
        "energy": 35,
        "nameid": "SWIFT",
        "buffChance": 0,
        "buffSelf": false,
        "buffEffect": "",
        "name": "Swift",
        "type": "normal",
        "damage": 55,
        "turns": 0
    },
    {
        "energy": 50,
        "nameid": "SYNCHRONOISE",
        "buffChance": 0,
        "buffSelf": false,
        "buffEffect": "",
        "name": "Synchronoise",
        "type": "psychic",
        "damage": 80,
        "turns": 0
    },
    {
        "energy": 3,
        "nameid": "TACKLE",
        "buffChance": 0,
        "buffSelf": false,
        "buffEffect": "",
        "name": "Tackle",
        "type": "normal",
        "damage": 3,
        "turns": 1
    },
    {
        "energy": 8,
        "nameid": "TAKE_DOWN",
        "buffChance": 0,
        "buffSelf": false,
        "buffEffect": "",
        "name": "Take Down",
        "type": "normal",
        "damage": 5,
        "turns": 3
    },
    {
        "energy": 55,
        "nameid": "TECHNO_BLAST_BURN",
        "buffChance": 0,
        "buffSelf": false,
        "buffEffect": "",
        "name": "Techno Blast (Burn)",
        "type": "fire",
        "damage": 120,
        "turns": 0
    },
    {
        "energy": 55,
        "nameid": "TECHNO_BLAST_CHILL",
        "buffChance": 0,
        "buffSelf": false,
        "buffEffect": "",
        "name": "Techno Blast (Chill)",
        "type": "ice",
        "damage": 120,
        "turns": 0
    },
    {
        "energy": 55,
        "nameid": "TECHNO_BLAST_DOUSE",
        "buffChance": 0,
        "buffSelf": false,
        "buffEffect": "",
        "name": "Techno Blast (Douse)",
        "type": "water",
        "damage": 120,
        "turns": 0
    },
    {
        "energy": 55,
        "nameid": "TECHNO_BLAST_NORMAL",
        "buffChance": 0,
        "buffSelf": false,
        "buffEffect": "",
        "name": "Techno Blast (Normal)",
        "type": "normal",
        "damage": 120,
        "turns": 0
    },
    {
        "energy": 55,
        "nameid": "TECHNO_BLAST_SHOCK",
        "buffChance": 0,
        "buffSelf": false,
        "buffEffect": "",
        "name": "Techno Blast (Shock)",
        "type": "electric",
        "damage": 120,
        "turns": 0
    },
    {
        "energy": 60,
        "nameid": "THUNDER",
        "buffChance": 0,
        "buffSelf": false,
        "buffEffect": "",
        "name": "Thunder",
        "type": "electric",
        "damage": 100,
        "turns": 0
    },
    {
        "energy": 55,
        "nameid": "THUNDERBOLT",
        "buffChance": 0,
        "buffSelf": false,
        "buffEffect": "",
        "name": "Thunderbolt",
        "type": "electric",
        "damage": 90,
        "turns": 0
    },
    {
        "energy": 40,
        "nameid": "THUNDER_CAGE",
        "buffChance": "1",
        "buffSelf": false,
        "buffEffect": " -1 DEF",
        "name": "Thunder Cage",
        "type": "electric",
        "damage": 60,
        "turns": 0
    },
    {
        "energy": 6,
        "nameid": "THUNDER_FANG",
        "buffChance": 0,
        "buffSelf": false,
        "buffEffect": "",
        "name": "Thunder Fang",
        "type": "electric",
        "damage": 8,
        "turns": 2
    },
    {
        "energy": 40,
        "nameid": "THUNDER_PUNCH",
        "buffChance": 0,
        "buffSelf": false,
        "buffEffect": "",
        "name": "Thunder Punch",
        "type": "electric",
        "damage": 60,
        "turns": 0
    },
    {
        "energy": 9,
        "nameid": "THUNDER_SHOCK",
        "buffChance": 0,
        "buffSelf": false,
        "buffEffect": "",
        "name": "Thunder Shock",
        "type": "electric",
        "damage": 4,
        "turns": 2
    },
    {
        "energy": 45,
        "nameid": "TORCH_SONG",
        "buffChance": "1",
        "buffSelf": true,
        "buffEffect": "+1 ATK",
        "name": "Torch Song",
        "type": "fire",
        "damage": 70,
        "turns": 0
    },
    {
        "energy": 45,
        "nameid": "TRAILBLAZE",
        "buffChance": "1",
        "buffSelf": true,
        "buffEffect": "+1 ATK",
        "name": "Trailblaze",
        "type": "grass",
        "damage": 65,
        "turns": 0
    },
    {
        "energy": 0,
        "nameid": "TRANSFORM",
        "buffChance": 0,
        "buffSelf": false,
        "buffEffect": "",
        "name": "Transform",
        "type": "normal",
        "damage": 0,
        "turns": 0
    },
    {
        "energy": 45,
        "nameid": "TRIPLE_AXEL",
        "buffChance": "1",
        "buffSelf": true,
        "buffEffect": "+1 ATK",
        "name": "Triple Axel",
        "type": "ice",
        "damage": 60,
        "turns": 0
    },
    {
        "energy": 50,
        "nameid": "TRI_ATTACK",
        "buffChance": ".5",
        "buffSelf": false,
        "buffEffect": "-1 ATK -1 DEF",
        "name": "Tri Attack",
        "type": "normal",
        "damage": 65,
        "turns": 0
    },
    {
        "energy": 45,
        "nameid": "TWISTER",
        "buffChance": 0,
        "buffSelf": false,
        "buffEffect": "",
        "name": "Twister",
        "type": "dragon",
        "damage": 45,
        "turns": 0
    },
    {
        "energy": 40,
        "nameid": "UPPER_HAND",
        "buffChance": ".3",
        "buffSelf": false,
        "buffEffect": " -1 DEF",
        "name": "Upper Hand",
        "type": "fighting",
        "damage": 70,
        "turns": 0
    },
    {
        "energy": 40,
        "nameid": "VICE_GRIP",
        "buffChance": 0,
        "buffSelf": false,
        "buffEffect": "",
        "name": "Vise Grip",
        "type": "normal",
        "damage": 70,
        "turns": 0
    },
    {
        "energy": 8,
        "nameid": "VINE_WHIP",
        "buffChance": 0,
        "buffSelf": false,
        "buffEffect": "",
        "name": "Vine Whip",
        "type": "grass",
        "damage": 5,
        "turns": 2
    },
    {
        "energy": 16,
        "nameid": "VOLT_SWITCH",
        "buffChance": 0,
        "buffSelf": false,
        "buffEffect": "",
        "name": "Volt Switch",
        "type": "electric",
        "damage": 14,
        "turns": 4
    },
    {
        "energy": 50,
        "nameid": "VOLT_TACKLE",
        "buffChance": "1",
        "buffSelf": true,
        "buffEffect": " -1 DEF",
        "name": "Volt Tackle",
        "type": "electric",
        "damage": 90,
        "turns": 0
    },
    {
        "energy": 40,
        "nameid": "V_CREATE",
        "buffChance": "1",
        "buffSelf": true,
        "buffEffect": " -3 DEF",
        "name": "V-Create",
        "type": "fire",
        "damage": 95,
        "turns": 0
    },
    {
        "energy": 8,
        "nameid": "WATERFALL",
        "buffChance": 0,
        "buffSelf": false,
        "buffEffect": "",
        "name": "Waterfall",
        "type": "water",
        "damage": 12,
        "turns": 3
    },
    {
        "energy": 3,
        "nameid": "WATER_GUN",
        "buffChance": 0,
        "buffSelf": false,
        "buffEffect": "",
        "name": "Water Gun",
        "type": "water",
        "damage": 3,
        "turns": 1
    },
    {
        "energy": 4,
        "nameid": "WATER_GUN_FAST_BLASTOISE",
        "buffChance": 0,
        "buffSelf": false,
        "buffEffect": "",
        "name": "Water Gun Fast Blastoise",
        "type": "water",
        "damage": 6,
        "turns": 2
    },
    {
        "energy": 50,
        "nameid": "WATER_PULSE",
        "buffChance": 0,
        "buffSelf": false,
        "buffEffect": "",
        "name": "Water Pulse",
        "type": "water",
        "damage": 80,
        "turns": 0
    },
    {
        "energy": 14,
        "nameid": "WATER_SHURIKEN",
        "buffChance": 0,
        "buffSelf": false,
        "buffEffect": "",
        "name": "Water Shuriken",
        "type": "water",
        "damage": 6,
        "turns": 3
    },
    {
        "energy": 35,
        "nameid": "WEATHER_BALL_FIRE",
        "buffChance": 0,
        "buffSelf": false,
        "buffEffect": "",
        "name": "Weather Ball (Fire)",
        "type": "fire",
        "damage": 60,
        "turns": 0
    },
    {
        "energy": 35,
        "nameid": "WEATHER_BALL_ICE",
        "buffChance": 0,
        "buffSelf": false,
        "buffEffect": "",
        "name": "Weather Ball (Ice)",
        "type": "ice",
        "damage": 60,
        "turns": 0
    },
    {
        "energy": 35,
        "nameid": "WEATHER_BALL_NORMAL",
        "buffChance": 0,
        "buffSelf": false,
        "buffEffect": "",
        "name": "Weather Ball (Normal)",
        "type": "normal",
        "damage": 60,
        "turns": 0
    },
    {
        "energy": 35,
        "nameid": "WEATHER_BALL_ROCK",
        "buffChance": 0,
        "buffSelf": false,
        "buffEffect": "",
        "name": "Weather Ball (Rock)",
        "type": "rock",
        "damage": 60,
        "turns": 0
    },
    {
        "energy": 35,
        "nameid": "WEATHER_BALL_WATER",
        "buffChance": 0,
        "buffSelf": false,
        "buffEffect": "",
        "name": "Weather Ball (Water)",
        "type": "water",
        "damage": 60,
        "turns": 0
    },
    {
        "energy": 45,
        "nameid": "WILDBOLT_STORM",
        "buffChance": "1",
        "buffSelf": false,
        "buffEffect": "-1 ATK",
        "name": "Wildbolt Storm",
        "type": "electric",
        "damage": 60,
        "turns": 0
    },
    {
        "energy": 45,
        "nameid": "WILD_CHARGE",
        "buffChance": "1",
        "buffSelf": true,
        "buffEffect": " -2 DEF",
        "name": "Wild Charge",
        "type": "electric",
        "damage": 100,
        "turns": 0
    },
    {
        "energy": 7,
        "nameid": "WING_ATTACK",
        "buffChance": 0,
        "buffSelf": false,
        "buffEffect": "",
        "name": "Wing Attack",
        "type": "flying",
        "damage": 5,
        "turns": 2
    },
    {
        "energy": 45,
        "nameid": "WRAP",
        "buffChance": "1",
        "buffSelf": false,
        "buffEffect": " -1 DEF",
        "name": "Wrap",
        "type": "normal",
        "damage": 60,
        "turns": 0
    },
    {
        "energy": 40,
        "nameid": "X_SCISSOR",
        "buffChance": 0,
        "buffSelf": false,
        "buffEffect": "",
        "name": "X-Scissor",
        "type": "bug",
        "damage": 65,
        "turns": 0
    },
    {
        "energy": 12,
        "nameid": "YAWN",
        "buffChance": 0,
        "buffSelf": false,
        "buffEffect": "",
        "name": "Yawn",
        "type": "normal",
        "damage": 0,
        "turns": 4
    },
    {
        "energy": 80,
        "nameid": "ZAP_CANNON",
        "buffChance": ".33",
        "buffSelf": false,
        "buffEffect": "-1 ATK",
        "name": "Zap Cannon",
        "type": "electric",
        "damage": 150,
        "turns": 0
    },
    {
        "energy": 6,
        "nameid": "ZEN_HEADBUTT",
        "buffChance": 0,
        "buffSelf": false,
        "buffEffect": "",
        "name": "Zen Headbutt",
        "type": "psychic",
        "damage": 8,
        "turns": 3
    },
    {
        "energy": 8,
        "nameid": "HIDDEN_POWER",
        "buffChance": 0,
        "buffSelf": false,
        "buffEffect": "",
        "name": "Hidden Power",
        "type": "normal",
        "damage": 9,
        "turns": 3
    }
]
